drf_utilities-0.0.1.dist-info/licenses/LICENSE
rest_framework_utils/__init__.py
rest_framework_utils/serializers.py
drf_utilities-0.0.1.dist-info/METADATA
drf_utilities-0.0.1.dist-info/WHEEL
drf_utilities-0.0.1.dist-info/top_level.txt
drf_utilities-0.0.1.dist-info/RECORD
