Metadata-Version: 2.4
Name: drf_utilities
Version: 0.0.1
Summary: Extended utilities for django rest framework
Requires-Python: >=3.8
License-File: LICENSE
Dynamic: license-file
